{
  "surface": {
    "--cream":         "#faf9f5",
    "--cream-soft":    "#f5f4ed",
    "--ivory":         "#fffefa",
    "--rule":          "#d6d3c8",
    "--rule-soft":     "#e5e3d8"
  },
  "text": {
    "--ink":           "#1a1a1a",
    "--ink-soft":      "#3d3d3a",
    "--ink-muted":     "#6b6a64",
    "--ink-faint":     "#8c8a82"
  },
  "accent": {
    "--accent-clay":         "#d97757",
    "--accent-clay-tint":    "#f0d5c7",
    "--accent-sage":         "#629987",
    "--accent-sage-tint":    "#bcd1ca",
    "--accent-iris":         "#827dbd",
    "--accent-iris-tint":    "#cbcadb",
    "--accent-ink":          "#1B365D",
    "--accent-ink-tint":     "#E4ECF5",
    "--accent-rust":         "#a04b3a",
    "--accent-rust-tint":    "#e6c8be"
  },
  "type": {
    "--font-serif": "\"Fraunces\", \"Tiempos Text\", \"Source Serif Pro\", \"Iowan Old Style\", Georgia, serif",
    "--font-sans":  "\"Inter Tight\", \"Inter\", -apple-system, BlinkMacSystemFont, \"Segoe UI\", sans-serif",
    "--font-mono":  "\"JetBrains Mono\", \"SF Mono\", Menlo, Consolas, monospace",
    "--serif-display-axes": "\"opsz\" 144, \"SOFT\" 30",
    "--serif-h2-axes":      "\"opsz\" 60,  \"SOFT\" 40",
    "--serif-text-axes":    "\"opsz\" 14,  \"SOFT\" 50"
  },
  "size_print_pt": {
    "display":     36,
    "h1":          22,
    "h2":          16,
    "h3":          13,
    "lead":        11,
    "body":        10,
    "body_dense":  9.2,
    "caption":     9,
    "label":       9,
    "tiny":        8.5
  },
  "spacing_pt": {
    "xs":  3,
    "sm":  5,
    "md":  10,
    "lg":  18,
    "xl":  28,
    "2xl": 50,
    "3xl": 90
  },
  "page": {
    "size": "A4",
    "size_us": "letter",
    "margin_mm": [22, 24, 24, 22],
    "orientation_default": "portrait",
    "orientation_landscape_alt": true
  },
  "rules": {
    "max_accent_surface_ratio_per_page": 0.15,
    "max_accent_surface_ratio_doc_avg":  0.05,
    "min_lines_per_paragraph_at_page_end": 2,
    "max_callouts_per_spread": 2,
    "cadence_visual_reset_every_n_pages": [5, 7]
  }
}
